countASAP/__init__.py
countASAP/asap_process.py
countASAP/get_tests.py
countASAP/run_process.sh
countASAP/ATAC_process/plot_umap.py
countASAP/ATAC_process/process_ATAC_template.R
countASAP/ATAC_process/process_atac.sh
countASAP/ex_inputs/asapSeq_barcodes.csv
countASAP/ex_inputs/whitelist_ex.csv
countASAP-0.2.dist-info/LICENSE
countASAP-0.2.dist-info/METADATA
countASAP-0.2.dist-info/WHEEL
countASAP-0.2.dist-info/entry_points.txt
countASAP-0.2.dist-info/top_level.txt
countASAP-0.2.dist-info/RECORD
