Metadata-Version: 2.1
Name: countASAP
Version: 0.2
Summary: A software for converting ASAPseq FASTQs to count matrices
Author-email: Chris Boughter <ctboughter@gmail.com>
Project-URL: Homepage, https://github.com/ctboughter/countASAP
Project-URL: Bug Tracker, https://github.com/ctboughter/countASAP/issues
Classifier: Programming Language :: Python :: 3
Classifier: License :: OSI Approved :: MIT License
Classifier: Operating System :: OS Independent
Requires-Python: >=3.7
License-File: LICENSE
Requires-Dist: requests
Requires-Dist: rapidfuzz ==3.5.2
Requires-Dist: anndata ==0.9.2
Requires-Dist: pandas ==2.0.3
Requires-Dist: numpy ==1.24.4
Requires-Dist: matplotlib ==3.7.3
Requires-Dist: biopython ==1.81
Requires-Dist: importlib-metadata ; python_version < "3.7"
